odoo/addons/fleet_vehicle_inspection/README.rst
odoo/addons/fleet_vehicle_inspection/__init__.py
odoo/addons/fleet_vehicle_inspection/__manifest__.py
odoo/addons/fleet_vehicle_inspection/data/fleet_vehicle_inspection.xml
odoo/addons/fleet_vehicle_inspection/demo/fleet_vehicle_inspection.xml
odoo/addons/fleet_vehicle_inspection/i18n/es.po
odoo/addons/fleet_vehicle_inspection/i18n/fleet_vehicle_inspection.pot
odoo/addons/fleet_vehicle_inspection/i18n/it.po
odoo/addons/fleet_vehicle_inspection/i18n/pt_BR.po
odoo/addons/fleet_vehicle_inspection/models/__init__.py
odoo/addons/fleet_vehicle_inspection/models/fleet_vehicle.py
odoo/addons/fleet_vehicle_inspection/models/fleet_vehicle_inspection.py
odoo/addons/fleet_vehicle_inspection/models/fleet_vehicle_inspection_item.py
odoo/addons/fleet_vehicle_inspection/models/fleet_vehicle_inspection_line.py
odoo/addons/fleet_vehicle_inspection/models/fleet_vehicle_inspection_line_image.py
odoo/addons/fleet_vehicle_inspection/readme/CONFIGURE.md
odoo/addons/fleet_vehicle_inspection/readme/CONTRIBUTORS.md
odoo/addons/fleet_vehicle_inspection/readme/CREDITS.md
odoo/addons/fleet_vehicle_inspection/readme/DESCRIPTION.md
odoo/addons/fleet_vehicle_inspection/readme/ROADMAP.md
odoo/addons/fleet_vehicle_inspection/security/ir.model.access.csv
odoo/addons/fleet_vehicle_inspection/security/security.xml
odoo/addons/fleet_vehicle_inspection/static/description/banner.png
odoo/addons/fleet_vehicle_inspection/static/description/icon.png
odoo/addons/fleet_vehicle_inspection/static/description/index.html
odoo/addons/fleet_vehicle_inspection/tests/__init__.py
odoo/addons/fleet_vehicle_inspection/tests/test_fleet_vehicle_inspection.py
odoo/addons/fleet_vehicle_inspection/views/fleet_vehicle_inspection_item_views.xml
odoo/addons/fleet_vehicle_inspection/views/fleet_vehicle_inspection_line_views.xml
odoo/addons/fleet_vehicle_inspection/views/fleet_vehicle_inspection_views.xml
odoo/addons/fleet_vehicle_inspection/views/fleet_vehicle_views.xml
odoo_addon_fleet_vehicle_inspection-18.0.1.0.0.8.dist-info/METADATA
odoo_addon_fleet_vehicle_inspection-18.0.1.0.0.8.dist-info/WHEEL
odoo_addon_fleet_vehicle_inspection-18.0.1.0.0.8.dist-info/top_level.txt
odoo_addon_fleet_vehicle_inspection-18.0.1.0.0.8.dist-info/RECORD
